{
  "name": "generateWidgetCard",
  "transport": "websocket",
  "path": "/genui-agent-service/api/v1/ws/tools/generateWidgetCard",
  "description": "提交用户需求、候选数据绑定、候选事件和素材，生成可下载的 HarmonyOS A2UI Form 卡片 artifact。content 对应业务入参。",
  "messageEnvelope": {
    "type": "object",
    "required": ["content", "deviceInfo", "session"],
    "properties": {
      "content": {
        "type": "object",
        "required": true,
        "description": "业务入参，对应旧协议 arguments。",
        "requiredProperties": ["userQuery", "title", "description"],
        "properties": {
          "bundleName": {
            "type": "string",
            "required": false,
            "description": "宿主业务包名。"
          },
          "userQuery": {
            "type": "string",
            "required": true,
            "description": "用户原始卡片需求；缺失时服务会尝试使用 utterance.original 兜底。"
          },
          "size": {
            "type": "string",
            "enum": ["2x2", "2x4"],
            "required": false,
            "default": "2x4",
            "description": "主 Agent 建议尺寸。"
          },
          "title": {
            "type": "string",
            "required": true,
            "minLength": 1,
            "description": "主 Agent 建议的卡片标题；会进入 TaskSpec.title，并作为 A2UI 标题候选。"
          },
          "description": {
            "type": "string",
            "required": true,
            "minLength": 1,
            "description": "主 Agent 建议的卡片说明；会进入 TaskSpec.description，并作为 A2UI 摘要候选。"
          },
          "candidateDataBindings": {
            "type": "CandidateDataBinding[]",
            "required": false,
            "description": "候选数据能力调用列表；微服务会按注册表和 IDS 状态裁决最终可用项。"
          },
          "candidateEventCandidates": {
            "type": "CandidateEventCandidate[]",
            "required": false,
            "description": "候选点击事件列表；action 只能来自能力概述返回的事件能力说明。"
          },
          "candidateAssetIds": {
            "type": "string[]",
            "required": false,
            "description": "候选素材 ID 列表。"
          },
          "capabilityRegistryVersion": {
            "type": "string|null",
            "required": false,
            "description": "可选能力清单版本；不传时由 deviceInfo.prdVer + ROM 版本推导。"
          },
          "protocolProfileId": {
            "type": "string|null",
            "required": false,
            "description": "可选 A2UI 协议 profile ID；不传时使用默认 profile。"
          }
        }
      },
      "deviceInfo": {
        "$ref": "#/nestedTypes/DeviceInfo",
        "required": true,
        "description": "端侧设备信息；缺少 ROM 字段时服务使用 settings.default_device_rom_version。版本目录由 prdVer + ROM 版本组成。"
      },
      "session": {
        "$ref": "#/nestedTypes/Session",
        "required": true,
        "description": "会话信息；服务端 requestId = sessionId + '&' + interactionId。"
      },
      "pagination": {
        "$ref": "#/nestedTypes/Pagination",
        "required": false,
        "description": "分页信息，当前接口暂不消费。"
      },
      "userAuth": {
        "$ref": "#/nestedTypes/UserAuth",
        "required": false,
        "description": "用户鉴权信息；服务从 user.userId 提取 uid。"
      },
      "utterance": {
        "$ref": "#/nestedTypes/Utterance",
        "required": false,
        "description": "用户原始表达；content.userQuery 缺失时可作为兜底。"
      },
      "version": {
        "type": "string",
        "required": false,
        "description": "外部包络协议版本。"
      },
      "bundleName": {
        "type": "string",
        "required": false,
        "description": "外层宿主业务包名。"
      }
    }
  },
  "output": {
    "type": "object",
    "required": ["errorCode", "errorMessage", "reply"],
    "properties": {
      "errorCode": {
        "type": "string",
        "required": true,
        "description": "华为流处理插件顶层响应码；成功、降级成功和业务 unsupported 通常为 0，参数错误、系统异常或工程 failed 时为非 0。"
      },
      "errorMessage": {
        "type": "string",
        "required": true,
        "description": "顶层错误描述；成功、降级或业务 unsupported 时为空字符串。"
      },
      "reply": {
        "type": "object",
        "required": true,
        "description": "流处理插件响应内容。",
        "requiredProperties": ["streamInfo", "items"],
        "properties": {
          "streamInfo": {
            "$ref": "#/nestedTypes/StreamInfo",
            "required": true,
            "description": "答复文本结构；当前服务一次请求只发送 final 帧。"
          },
          "items": {
            "type": "GenerateWidgetCardResult[]",
            "required": true,
            "minItems": 1,
            "description": "结构化数据；items[0] 保留当前完整旧出参 type/tool/operation/requestId/data/status/errorCode/error。"
          }
        }
      }
    }
  },
  "nestedTypes": {
    "StreamInfo": {
      "required": ["streamContent", "streamingTextId", "streamType", "textType"],
      "properties": {
        "streamContent": "string，截止当前帧的全量输出内容；生成接口优先使用业务响应 message。",
        "streamingTextId": "string，流式文本 ID；当前使用 requestId，缺失时生成随机 ID。",
        "streamType": "string，当前固定为 final。",
        "textType": "string，当前固定为 markdown。"
      }
    },
    "GenerateWidgetCardResult": {
      "required": ["type", "tool", "operation", "requestId", "data", "status", "errorCode", "error"],
      "properties": {
        "type": "string，旧完整出参消息类型；正常为 result，异常为 error。",
        "tool": "string，当前工具名；本接口为 generateWidgetCard。",
        "operation": "string，当前 WebSocket path 对应的接口名。",
        "requestId": "string|null，服务端根据 sessionId + '&' + interactionId 生成的请求 ID。",
        "data.apiVersion": "string，接口版本。",
        "data.status": "string，生成状态，枚举 success/degraded/unsupported/failed。",
        "data.artifactUrl": "string，artifact 下载地址；成功或降级成功时返回。",
        "data.artifactDigest": "string，artifact 内容摘要。",
        "data.suggestSize": "string，最终生成卡片尺寸，枚举 2x2/2x4。",
        "data.message": "string，可展示给主 Agent 或用户的生成结果说明。",
        "data.removedCapabilities": "RemovedCapability[]，被微服务裁决移除的能力及原因。",
        "data.errorCode": "string，失败或不支持时返回的错误码。",
        "data.artifact": "object|null，调试时可选内联 artifact；生产默认不返回。artifact.taskSpec 会包含 userQuery/size/title/description/eventCandidates/dataModel/assetCandidates。",
        "data.effectiveCapabilities": "object，最终进入 artifact 的有效 data、event、asset 能力集合。",
        "status": "string，旧完整出参调用状态；生成接口透传 data.status。",
        "errorCode": "string，旧完整出参错误码；生成接口透传 data.errorCode。",
        "error": "object，旧完整出参错误详情；成功、降级或业务 unsupported 通常为空对象。"
      }
    },
    "CandidateDataBinding": {
      "required": ["capabilityId", "arguments", "writeResultTo"],
      "properties": {
        "capabilityId": "string，数据能力 ID。",
        "arguments": "object，能力入参，只能使用该能力 inputSchema 声明的字段。",
        "writeResultTo": "string，写入 DataModel 的 JSON Pointer，必须位于 /data/ 下。",
        "updateModel": "object，可选输出字段投影结构，内部层级会原样写入 DataModel。"
      }
    },
    "CandidateEventCandidate": {
      "required": ["capabilityId", "action"],
      "properties": {
        "capabilityId": "string，事件能力 ID。",
        "action.call": "string，事件调用名，例如 clickToDeeplink、clickToIntent、clickToApi。",
        "action.args": "object，事件参数对象。"
      }
    },
    "DeviceInfo": {
      "required": ["locale", "phoneType", "sysVer"],
      "properties": {
        "countryCode": "string，可选，国家码。",
        "deviceFormation": "string，可选，设备形态。",
        "deviceType": "integer|string，可选，设备类型编码。",
        "locale": "string，推荐，语言区域。",
        "phoneType": "string，推荐，设备型号。",
        "prdVer": "string，可选，端侧传入的业务 API 版本；字段名保持端侧协议原名。",
        "sysVer": "string，推荐，系统版本。",
        "time": "string，可选，端侧请求时间。",
        "romVersion|romVer|rom|rom_version|ohosApiVersion|ohos_api_version": "string|integer，可选，ROM 版本；缺失时使用配置默认 ROM。",
        "ohosApiVersion|ohos_api_version": "integer，可选；当前也可作为 ROM 版本兜底来源。"
      }
    },
    "Session": {
      "required": ["sessionId", "interactionId"],
      "properties": {
        "sessionId": "string，会话 ID。",
        "interactionId": "string，交互 ID。",
        "isNew": "boolean，可选，是否新会话。"
      }
    },
    "UserAuth": {
      "required": false,
      "properties": {
        "user.userId": "string，可选，用户 ID。"
      }
    },
    "Pagination": {
      "required": false,
      "properties": {
        "limit": "integer，可选，分页大小。",
        "start": "string，可选，分页游标。"
      }
    },
    "Utterance": {
      "required": false,
      "properties": {
        "original": "string，可选，用户原始表达。",
        "type": "string，可选，输入类型。"
      }
    }
  }
}
